MANIFEST.in
README.txt
distribute_setup.py
setup.py
glimpse/__init__.py
glimpse.egg-info/PKG-INFO
glimpse.egg-info/SOURCES.txt
glimpse.egg-info/dependency_links.txt
glimpse.egg-info/entry_points.txt
glimpse.egg-info/requires.txt
glimpse.egg-info/top_level.txt
glimpse/backends/__init__.py
glimpse/backends/base_backend.py
glimpse/backends/base_backend_test.py
glimpse/backends/misc.py
glimpse/backends/misc_test.py
glimpse/backends/scipy_backend.py
glimpse/backends/base_backend/array.cpp
glimpse/backends/base_backend/array.h
glimpse/backends/base_backend/bitset_array.cpp
glimpse/backends/base_backend/bitset_array.h
glimpse/backends/base_backend/filter.cpp
glimpse/backends/base_backend/filter.h
glimpse/backends/base_backend/module.cpp
glimpse/backends/base_backend/util.cpp
glimpse/backends/base_backend/util.h
glimpse/corpora/__init__.py
glimpse/experiment/__init__.py
glimpse/experiment/experiment.py
glimpse/experiment/experiment_test.py
glimpse/experiment/mf_wkmeans.py
glimpse/experiment/misc.py
glimpse/experiment/om_wkmeans.py
glimpse/experiment/proto_utils.py
glimpse/experiment/prototype_algorithms.py
glimpse/experiment/prototype_algorithms_test.py
glimpse/experiment/utils.py
glimpse/experiment/utils_test.py
glimpse/glab/__init__.py
glimpse/glab/api.py
glimpse/glab/api_test.py
glimpse/glab/cli.py
glimpse/glab/cli_test.py
glimpse/glab/experiment/__init__.py
glimpse/glab/experiment/experiment.py
glimpse/glab/ui/__init__.py
glimpse/glab/ui/glab_main.py
glimpse/glab/ui/glab_wizard.py
glimpse/models/__init__.py
glimpse/models/misc.py
glimpse/models/misc_test.py
glimpse/models/base/__init__.py
glimpse/models/base/layer.py
glimpse/models/base/layer_test.py
glimpse/models/base/misc.py
glimpse/models/base/misc_test.py
glimpse/models/base/model.py
glimpse/models/base/model_test.py
glimpse/models/base/param.py
glimpse/models/base/param_test.py
glimpse/models/ml/__init__.py
glimpse/models/ml/misc.py
glimpse/models/ml/model.py
glimpse/models/ml/model_test.py
glimpse/models/ml/param.py
glimpse/pools/__init__.py
glimpse/pools/misc.py
glimpse/pools/misc_test.py
glimpse/pools/gearmancluster/__init__.py
glimpse/pools/gearmancluster/main.py
