Metadata-Version: 1.1
Name: glimpse
Version: 0.2.1
Summary: Hierarchical visual models in C++ and Python
Home-page: https://github.com/mthomure/glimpse-project
Author: Mick Thomure
Author-email: thomure@cs.pdx.edu
License: LICENSE.txt
Platform: Linux
Platform: Mac OS-X
Platform: Unix
Classifier: Development Status :: 3 - Alpha
Classifier: Intended Audience :: Science/Research
Classifier: Intended Audience :: Developers
Classifier: License :: OSI Approved :: MIT License
Classifier: Programming Language :: C++
Classifier: Programming Language :: Python
Classifier: Topic :: Software Development
Classifier: Topic :: Scientific/Engineering
Classifier: Operating System :: Microsoft :: Windows
Classifier: Operating System :: POSIX
Classifier: Operating System :: Unix
Classifier: Operating System :: MacOS
